asdf_coordinates_schemas/__init__.py
asdf_coordinates_schemas/_version.py
asdf_coordinates_schemas/integration.py
asdf_coordinates_schemas/resources/manifests/coordinates-1.0.0.yaml
asdf_coordinates_schemas/resources/schemas/angle-1.0.0.yaml
asdf_coordinates_schemas/resources/schemas/earthlocation-1.0.0.yaml
asdf_coordinates_schemas/resources/schemas/latitude-1.0.0.yaml
asdf_coordinates_schemas/resources/schemas/longitude-1.0.0.yaml
asdf_coordinates_schemas/resources/schemas/representation-1.0.0.yaml
asdf_coordinates_schemas/resources/schemas/skycoord-1.0.0.yaml
asdf_coordinates_schemas/resources/schemas/spectralcoord-1.0.0.yaml
asdf_coordinates_schemas/resources/schemas/frames/baseframe-1.0.0.yaml
asdf_coordinates_schemas/resources/schemas/frames/cirs-1.0.0.yaml
asdf_coordinates_schemas/resources/schemas/frames/fk4-1.0.0.yaml
asdf_coordinates_schemas/resources/schemas/frames/fk4noeterms-1.0.0.yaml
asdf_coordinates_schemas/resources/schemas/frames/fk5-1.0.0.yaml
asdf_coordinates_schemas/resources/schemas/frames/galactic-1.0.0.yaml
asdf_coordinates_schemas/resources/schemas/frames/galactocentric-1.0.0.yaml
asdf_coordinates_schemas/resources/schemas/frames/gcrs-1.0.0.yaml
asdf_coordinates_schemas/resources/schemas/frames/icrs-1.0.0.yaml
asdf_coordinates_schemas/resources/schemas/frames/icrs-1.1.0.yaml
asdf_coordinates_schemas/resources/schemas/frames/itrs-1.0.0.yaml
asdf_coordinates_schemas/resources/schemas/frames/precessedgeocentric-1.0.0.yaml
asdf_coordinates_schemas-0.2.0.dist-info/LICENSE
asdf_coordinates_schemas-0.2.0.dist-info/METADATA
asdf_coordinates_schemas-0.2.0.dist-info/WHEEL
asdf_coordinates_schemas-0.2.0.dist-info/entry_points.txt
asdf_coordinates_schemas-0.2.0.dist-info/top_level.txt
asdf_coordinates_schemas-0.2.0.dist-info/RECORD
