Metadata-Version: 2.1
Name: asdf-coordinates-schemas
Version: 0.2.0
Summary: ASDF schemas for coordinates
Author-email: The ASDF Developers <help@stsci.edu>
License: Copyright (c) 2021 Association of Universities for Research in Astronomy.
Project-URL: tracker, https://github.com/asdf-format/asdf-coordinates-schemas/issues
Project-URL: documentation, https://asdf-coordinates-schemas.readthedocs.io/en/latest/
Project-URL: repository, https://github.com/asdf-format/asdf-coordinates-schemas
Classifier: Programming Language :: Python
Classifier: Programming Language :: Python :: 3
Classifier: Programming Language :: Python :: 3.8
Classifier: Programming Language :: Python :: 3.9
Classifier: Programming Language :: Python :: 3.10
Classifier: Development Status :: 5 - Production/Stable
Classifier: Intended Audience :: Science/Research
Classifier: Topic :: Scientific/Engineering :: Astronomy
Requires-Python: >=3.8
Provides-Extra: docs
Provides-Extra: test
License-File: LICENSE
